<mods xmlns="http://www.loc.gov/mods/v3" xmlns:mods="http://www.loc.gov/mods/v3" xmlns:xsi="http://www.w3.org/2001/XMLSchema-instance" xmlns:xlink="http://www.w3.org/1999/xlink">
  <titleInfo>
    <title>Taraneha ve Khatereha Programme Number Thirteen &#1578;&#1585;&#1575;&#1606;&#1607;&#8204;&#1607;&#1575; &#1608; &#1582;&#1575;&#1591;&#1585;&#1607;&#8204;&#1607;&#1575;</title>
  </titleInfo>
  <name type="personal">
    <namePart>&#1578;&#1607;&#1740;&#1607;&#8204;&#1705;&#1606;&#1606;&#1583;&#1607;: &#1605;&#1581;&#1605;&#1583; &#1588;&#1608;&#1705;&#1578;</namePart>
    <role>
      <roleTerm authority="marcrelator" type="text">Producer</roleTerm>
    </role>
  </name>
  <name type="personal">
    <namePart>&#1605;&#1607;&#1585;&#1575;&#1606;&#1711;&#1740;&#1586; &#1582;&#1608;&#1575;&#1606;&#1587;&#1575;&#1585;&#1740;</namePart>
    <role>
      <roleTerm authority="marcrelator" type="text">Announcer</roleTerm>
    </role>
  </name>
  <name type="personal">
    <namePart>&#1575;&#1606;&#1608;&#1588;&#1610;&#1585;&#1608;&#1575;&#1606; &#1585;&#1608;&#1581;&#1575;&#1606;&#1740;  &#1575;&#1586; &#1576;&#1585;&#1606;&#1575;&#1605;&#1607; &#1588;&#1575;&#1582;&#1607; &#1711;&#1604; 80	Anoushirvan Rohani</namePart>
    <role>
      <roleTerm authority="marcrelator" type="text">Songwriter</roleTerm>
    </role>
  </name>
  <name type="personal">
    <namePart>&#1576;&#1583;&#1610;&#1593;&#8204;&#1586;&#1575;&#1583;&#1607; 	Badi Zade</namePart>
    <role>
      <roleTerm authority="marcrelator" type="text">Songwriter</roleTerm>
    </role>
  </name>
  <name type="personal">
    <namePart>&#1576;&#1586;&#1585;&#1711; &#1604;&#1588;&#1711;&#1585;&#1740;	Bozorg Lashgari</namePart>
    <role>
      <roleTerm authority="marcrelator" type="text">Songwriter</roleTerm>
    </role>
  </name>
  <name type="personal">
    <namePart>&#1578;&#1610;&#1605;&#1608;&#1585; &#1578;&#1575;&#1588;	Timur Tash</namePart>
    <role>
      <roleTerm authority="marcrelator" type="text">Songwriter</roleTerm>
    </role>
  </name>
  <name type="personal">
    <namePart>&#1593;&#1576;&#1575;&#1587; &#1605;&#1607;&#1585;&#1662;&#1608;&#1610;&#1575;	Abbas Mehrpoya</namePart>
    <role>
      <roleTerm authority="marcrelator" type="text">Songwriter</roleTerm>
    </role>
  </name>
  <name type="personal">
    <namePart>&#1585;&#1607;&#1740; &#1605;&#1593;&#1610;&#1585;&#1740;</namePart>
    <role>
      <roleTerm authority="marcrelator" type="text">Lyricist</roleTerm>
    </role>
  </name>
  <name type="personal">
    <namePart>&#1588;&#1607;&#1585;&#1570;&#1588;&#1608;&#1576;</namePart>
    <role>
      <roleTerm authority="marcrelator" type="text">Lyricist</roleTerm>
    </role>
  </name>
  <name type="personal">
    <namePart>&#1575;&#1705;&#1576;&#1585; &#1605;&#1581;&#1587;&#1606;&#1740;</namePart>
    <role>
      <roleTerm authority="marcrelator" type="text">Lyricist</roleTerm>
    </role>
  </name>
  <name type="personal">
    <namePart>&#1575;&#1605;&#1610;&#1585; &#1575;&#1576;&#1585;&#1575;&#1607;&#1610;&#1605;&#1740;</namePart>
    <role>
      <roleTerm authority="marcrelator" type="text">Lyricist</roleTerm>
    </role>
  </name>
  <name type="personal">
    <namePart>&#1662;&#1608;&#1585;&#1575;&#1606; 	Pouran</namePart>
    <role>
      <roleTerm authority="marcrelator" type="text">Singer</roleTerm>
    </role>
  </name>
  <name type="personal">
    <namePart>&#1576;&#1583;&#1610;&#1593; &#1586;&#1575;&#1583;&#1607; 	Badee zade</namePart>
    <role>
      <roleTerm authority="marcrelator" type="text">Singer</roleTerm>
    </role>
  </name>
  <name type="personal">
    <namePart>&#1610;&#1575;&#1587;&#1605;&#1610;&#1606;	Yasamin</namePart>
    <role>
      <roleTerm authority="marcrelator" type="text">Singer</roleTerm>
    </role>
  </name>
  <name type="personal">
    <namePart>&#1601;&#1585;&#1581;	Farah</namePart>
    <role>
      <roleTerm authority="marcrelator" type="text">Singer</roleTerm>
    </role>
  </name>
  <name type="personal">
    <namePart>&#1605;&#1607;&#1585;&#1662;&#1608;&#1610;&#1575;	Mehrpouya</namePart>
    <role>
      <roleTerm authority="marcrelator" type="text">Singer</roleTerm>
    </role>
  </name>
  <name type="corporate"/>
  <typeOfResource>Sound Recording</typeOfResource>
  <tableOfContents>&#1587;&#1585;&#1608; &#1670;&#1605;&#1606; 	Saro Chaman ( &#1575;&#1606;&#1608;&#1588;&#1610;&#1585;&#1608;&#1575;&#1606; &#1585;&#1608;&#1581;&#1575;&#1606;&#1740;  &#1575;&#1586; &#1576;&#1585;&#1606;&#1575;&#1605;&#1607; &#1588;&#1575;&#1582;&#1607; &#1711;&#1604; 80	Anoushirvan Rohani				&#1662;&#1608;&#1585;&#1575;&#1606; 	Pouran	&#1576;&#1610;&#1575;&#1578; &#1575;&#1589;&#1601;&#1607;&#1575;&#1606; 	Bayate Esfahan). --  &#1582;&#1586;&#1575;&#1606; &#1593;&#1588;&#1602;	khzane Eshk ( &#1576;&#1583;&#1610;&#1593;&#8204;&#1586;&#1575;&#1583;&#1607; 	Badi Zade	 &#1585;&#1607;&#1740; &#1605;&#1593;&#1610;&#1585;&#1740;			&#1576;&#1583;&#1610;&#1593; &#1586;&#1575;&#1583;&#1607; 	Badee zade	&#1607;&#1605;&#1575;&#1610;&#1608;&#1606; 	Homayun). --  &#1576;&#1586;&#1605; &#1588;&#1610;&#1585;&#1575;&#1586;	Bazme Shiraz ( &#1576;&#1586;&#1585;&#1711; &#1604;&#1588;&#1711;&#1585;&#1740;	Bozorg Lashgari	 &#1588;&#1607;&#1585;&#1570;&#1588;&#1608;&#1576;			&#1610;&#1575;&#1587;&#1605;&#1610;&#1606;	Yasamin	&#1587;&#1607;&#8204;&#1711;&#1575;&#1607; 	sekeh). --  &#1575;&#1608; &#1606;&#1610;&#1575;&#1605;&#1583;	o Nayamed ( &#1578;&#1610;&#1605;&#1608;&#1585; &#1578;&#1575;&#1588;	Timur Tash	 &#1575;&#1705;&#1576;&#1585; &#1605;&#1581;&#1587;&#1606;&#1740; 			&#1601;&#1585;&#1581;	Farah	&#1583;&#1588;&#1578;&#1740; 	Dashti). -- &#1601;&#1585;&#1583;&#1575;&#1740; &#1585;&#1608;&#1588;&#1606; 	Fardaye Roshan ( &#1593;&#1576;&#1575;&#1587; &#1605;&#1607;&#1585;&#1662;&#1608;&#1610;&#1575;	Abbas Mehrpoya	 &#1575;&#1605;&#1610;&#1585; &#1575;&#1576;&#1585;&#1575;&#1607;&#1610;&#1605;&#1740; 			&#1605;&#1607;&#1585;&#1662;&#1608;&#1610;&#1575;	Mehrpouya).</tableOfContents>
  <genre>radio program</genre>
  <originInfo>
    <dateIssued>1956-05-28</dateIssued>
  </originInfo>
  <language>
    <languageTerm authority="iso639-2b" type="code">per</languageTerm>
  </language>
  <abstract>&#1587;&#1585;&#1608; &#1670;&#1605;&#1606; &#1582;&#1605;&#1610;&#1583;&#1607; &#1578;&#1575; &#1705;&#1607; &#1578;&#1608; &#1585;&#1575; &#1583;&#1610;&#1583;&#1607; / &#1585;&#1606;&#1711; &#1587;&#1581;&#1585; &#1662;&#1585;&#1610;&#1583;&#1607;&#1548; &#1578;&#1575; &#1705;&#1607; &#1578;&#1608;&#1585;&#1575; &#1583;&#1610;&#1583;&#1607; / &#1583;&#1585;&#1578;&#1606; &#1670;&#1608; &#1605;&#1585;&#1605;&#1585;&#1578;&#1548; &#1575;&#1586; &#1602;&#1583;&#1605;&#1578; &#1578;&#1575; &#1587;&#1585;&#1578; / &#1583;&#1610;&#1583;&#1607; &#1575;&#1601;&#1587;&#1608;&#1606; &#1711;&#1585;&#1578; / &#1606;&#1608;&#1585; &#1608;&#1601;&#1575; &#1705;&#1608;&#1567;&#13;
&#1588;&#1583; &#1582;&#1586;&#1575;&#1606; &#1711;&#1604;&#1588;&#1606; &#1570;&#1588;&#1606;&#1575;&#1610;&#1740; / &#1576;&#1575;&#1586;&#1605; &#1570;&#1578;&#1588; &#1576;&#1607; &#1580;&#1575;&#1606; &#1586;&#1583; &#1580;&#1583;&#1575;&#1610;&#1740; / &#1593;&#1605;&#1585;&#1606; &#1605;&#1606; &#1575;&#1740; &#1711;&#1604;&#1548; &#1591;&#1740; &#1588;&#1583; &#1576;&#1607;&#1585; &#1578;&#1608; / &#1608;&#1586; &#1578;&#1608; &#1606;&#1583;&#1610;&#1583;&#1605;&#1548; &#1580;&#1586; &#1576;&#1583;&#1593;&#1607;&#1583;&#1740; &#1608; &#1576;&#1740;&#8204;&#1608;&#1601;&#1575;&#1610;&#1740; / &#1583;&#1585;&#1587;&#1575;&#1604; 1314 &#1590;&#1576;&#1591; &#1588;&#1583;&#1607; &#1575;&#1587;&#1578;.&#13;
&#1588;&#1610;&#1585;&#1575;&#1586;&#1548; &#1588;&#1610;&#1585;&#1575;&#1586;&#1548; &#1575;&#1740; &#1705;&#1608;&#1740; &#1580;&#1575;&#1606;&#1575;&#1606;&#1607; / &#1583;&#1585;&#1582;&#1608;&#1576;&#1740; &#1575;&#1601;&#1587;&#1575;&#1606;&#1607; / &#1575;&#1740; &#1583;&#1585; &#1576;&#1586;&#1605; &#1593;&#1588;&#1602;&#1578;&#1548; &#1589;&#1583; &#1593;&#1575;&#1602;&#1604; &#1583;&#1610;&#1608;&#1575;&#1606;&#1607; /&#1583;&#1585; &#1578;&#1575;&#1585;&#1610;&#1582; 1343/10/18 &#1662;&#1582;&#1588; &#1588;&#1583;&#1607; &#1575;&#1587;&#1578;. &#13;
&#1576;&#1607; &#1585;&#1575;&#1607; &#1608;&#1740;&#1548; &#1578;&#1575; &#1587;&#1581;&#1585; &#1605;&#1575;&#1606;&#1583;&#1605;&#1548; &#1688;&#1575;&#1604;&#1607; &#1575;&#1601;&#1588;&#1575;&#1606;&#1583;&#1605;&#1548; &#1575;&#1608; &#1606;&#1610;&#1575;&#1605;&#1583; / &#1576;&#1607; &#1575;&#1605;&#1610;&#1583;&#1588;&#1548; &#1576;&#1575;&#1606;&#1608;&#1575;&#1740; &#1583;&#1604;&#1548; &#1606;&#1594;&#1605;&#1607;&#8204;&#1607;&#1575; &#1582;&#1608;&#1575;&#1606;&#1583;&#1605;&#1548; &#1575;&#1608; &#1606;&#1610;&#1575;&#1605;&#1583; / &#1583;&#1585; &#1578;&#1575;&#1585;&#1740;&#1582; 1343/5/3 &#1662;&#1582;&#1588; &#1588;&#1583;&#1607; &#1575;&#1587;&#1578;.&#13;
&#1583;&#1585; &#1583;&#1604; &#1588;&#1576;&#1548; &#1605;&#1587;&#1578; &#1608; &#1588;&#1610;&#1583;&#1575; / &#1576;&#1575; &#1582;&#1610;&#1575;&#1604;&#1578; &#1605;&#1575;&#1606;&#1583;&#1607; &#1578;&#1606;&#1607;&#1575; / &#1587;&#1575;&#1594;&#1585; &#1605;&#1606; &#1582;&#1575;&#1604;&#1740; &#1575;&#1586; &#1605;&#1740; / &#1605;&#1740;&#8204;&#1711;&#1584;&#1575;&#1585;&#1605; &#1587;&#1585; &#1576;&#1607; &#1589;&#1581;&#1585;&#1575; / &#1593;&#1575;&#1588;&#1602;&#1740; &#1570;&#1586;&#1585;&#1583;&#1607; &#1576;&#1608;&#1583;&#1605; / &#1606;&#1594;&#1605;&#1607;  &#1594;&#1605; &#1605;&#1740;&#8204;&#1587;&#1585;&#1608;&#1583;&#1605;</abstract>
  <identifier>Taraneha va Khatereha 13</identifier>
  <physicalDescription>
    <form authority="marcform">sound recording</form>
    <extent>0:07:33</extent>
  </physicalDescription>
  <subject>
    <topic>Iranian National Radio</topic>
    <topic>radio programs</topic>
    <topic>music</topic>
    <topic>poetry</topic>
    <topic>&#1576;&#1610;&#1575;&#1578; &#1575;&#1589;&#1601;&#1607;&#1575;&#1606;</topic>
    <topic>Bayate Esfahan</topic>
    <topic>&#1607;&#1605;&#1575;&#1610;&#1608;&#1606;</topic>
    <topic>Homayun</topic>
    <topic>&#1587;&#1607;&#8204;&#1711;&#1575;&#1607;</topic>
    <topic>sekeh</topic>
    <topic>&#1583;&#1588;&#1578;&#1740;</topic>
    <topic>Dashti</topic>
    <geographic>Iran</geographic>
    <hierarchicalGeographic>
      <continent>Asia</continent>
      <country>Iran</country>
    </hierarchicalGeographic>
  </subject>
  <accessCondition type="useAndReproduction"/>
</mods>
